{
  "seed": 42,
  "pages_per_decade": 5,
  "n_total": 105,
  "decade_counts": {
    "1700": 5,
    "1710": 5,
    "1720": 5,
    "1730": 5,
    "1740": 5,
    "1750": 5,
    "1760": 5,
    "1770": 5,
    "1780": 5,
    "1790": 5,
    "1800": 5,
    "1810": 5,
    "1820": 5,
    "1830": 5,
    "1840": 5,
    "1850": 5,
    "1860": 5,
    "1870": 5,
    "1880": 5,
    "1890": 5,
    "1900": 5
  },
  "page_ids": [
    "1701_3_image",
    "1700_1_image",
    "1704_7_image",
    "1704_3_image",
    "1703_6_image",
    "1712_4_image",
    "1711_7_image",
    "1719_5_image",
    "1711_5_image",
    "1717_4_image",
    "1720_5_image",
    "1720_4_image",
    "1721-1722_1_image",
    "1724_1_image",
    "1724_3_image",
    "1734_4_image",
    "1735_5_image",
    "1730_2_image",
    "1735_2_image",
    "1731_4_image",
    "1747_4_image",
    "1746_7_image",
    "1747_3_image",
    "1745_6_image",
    "1744_5_image",
    "1753_6_image",
    "1757_5_image",
    "1759-1760_5_image",
    "1754_7_image",
    "1750_1_image",
    "1763_5_image",
    "1767-1768_13_image",
    "1766_2_image",
    "1765_3_image",
    "1763_4_image",
    "1773-1774_2_image",
    "1774-1775_7_image",
    "1771-1772_8_image",
    "1771-1772_6_image",
    "1775-1776_3_image",
    "1781-1782_3_image",
    "1785-1786_3_image",
    "1785-1786_2_image",
    "1788-1789_5_image",
    "1783-1784_6_image",
    "1790-1791_5_image",
    "1796-1797_2_image",
    "1797-1798_4_image",
    "1791-1792_6_image",
    "1795-1796_1_image",
    "1801_4_image",
    "1809_1_image",
    "1804_7_image",
    "1805_8_image",
    "1809_4_image",
    "1813_2_image",
    "1810_9_image",
    "1810_6_image",
    "1813_7_image",
    "1815_1_image",
    "1821_10_image",
    "1829_8_image",
    "1822_9_image",
    "1829_9_image",
    "1821_1_image",
    "1834_11_image",
    "1832_9_image",
    "1834_6_image",
    "1836_4_image",
    "1838_7_image",
    "1845_10_image",
    "1842_3_image",
    "1845_1_image",
    "1844_8_image",
    "1843_10_image",
    "1859_3_image",
    "1853_4_image",
    "1859_5_image",
    "1858_8_image",
    "1850_8_image",
    "1863_1_image",
    "1869_5_image",
    "1864_3_image",
    "1862_7_image",
    "1868_3_image",
    "1876_4_image",
    "1873_17_image",
    "1879_1_image",
    "1873_11_image",
    "1873_7_image",
    "1880_4_image",
    "1881_4_image",
    "1880_3_image",
    "1882_10_image",
    "1882_5_image",
    "1893_5_image",
    "1891_5_image",
    "1893_1_image",
    "1896_3_image",
    "1899_5_image",
    "1900_6_image",
    "1900_3_image",
    "1900_2_image",
    "1900_5_image",
    "1900_4_image"
  ]
}